django_dbcache_fields/__init__.py
django_dbcache_fields/apps.py
django_dbcache_fields/decorators.py
django_dbcache_fields/receivers.py
django_dbcache_fields/utils.py
django_dbcache_fields-0.9.3.dist-info/LICENSE
django_dbcache_fields-0.9.3.dist-info/METADATA
django_dbcache_fields-0.9.3.dist-info/WHEEL
django_dbcache_fields-0.9.3.dist-info/top_level.txt
django_dbcache_fields-0.9.3.dist-info/RECORD
